README.rst
setup.py
polyphony/__init__.py
polyphony/io.py
polyphony/timing.py
polyphony/typing.py
polyphony/verilog.py
polyphony/version.py
polyphony.egg-info/PKG-INFO
polyphony.egg-info/SOURCES.txt
polyphony.egg-info/dependency_links.txt
polyphony.egg-info/entry_points.txt
polyphony.egg-info/top_level.txt
polyphony/_internal/__init__.py
polyphony/_internal/_builtins.py
polyphony/_internal/_io.py
polyphony/_internal/_polyphony.py
polyphony/_internal/_timing.py
polyphony/_internal/_typing.py
polyphony/_internal/_verilog.py
polyphony/compiler/__init__.py
polyphony/compiler/__main__.py
polyphony/compiler/ahdl.py
polyphony/compiler/ahdlhelper.py
polyphony/compiler/ahdlusedef.py
polyphony/compiler/ahdlvisitor.py
polyphony/compiler/bitwidth.py
polyphony/compiler/block.py
polyphony/compiler/builtin.py
polyphony/compiler/cfgopt.py
polyphony/compiler/common.py
polyphony/compiler/constopt.py
polyphony/compiler/copyopt.py
polyphony/compiler/dataflow.py
polyphony/compiler/deadcode.py
polyphony/compiler/diagnostic.py
polyphony/compiler/dominator.py
polyphony/compiler/driver.py
polyphony/compiler/env.py
polyphony/compiler/errors.py
polyphony/compiler/graph.py
polyphony/compiler/hdlgen.py
polyphony/compiler/hdlinterface.py
polyphony/compiler/hdlmemport.py
polyphony/compiler/hdlmodule.py
polyphony/compiler/iftransform.py
polyphony/compiler/inlineopt.py
polyphony/compiler/instantiator.py
polyphony/compiler/iotransformer.py
polyphony/compiler/ir.py
polyphony/compiler/irhelper.py
polyphony/compiler/irtranslator.py
polyphony/compiler/irvisitor.py
polyphony/compiler/latency.py
polyphony/compiler/libs.py
polyphony/compiler/liveness.py
polyphony/compiler/loop.py
polyphony/compiler/loopdetector.py
polyphony/compiler/looptransformer.py
polyphony/compiler/memorytransform.py
polyphony/compiler/memref.py
polyphony/compiler/phiopt.py
polyphony/compiler/phiresolve.py
polyphony/compiler/portconverter.py
polyphony/compiler/pure.py
polyphony/compiler/quadruplet.py
polyphony/compiler/regreducer.py
polyphony/compiler/scheduler.py
polyphony/compiler/scope.py
polyphony/compiler/scopegraph.py
polyphony/compiler/selectorbuilder.py
polyphony/compiler/setlineno.py
