Metadata-Version: 1.0
Name: polyphony
Version: 0.3.4
Summary: Python based High Level Synthesis compiler
Home-page: https://github.com/ktok07b6/polyphony
Author: Hiroaki Kataoka
Author-email: kataoka@sinby.com
License: MIT
Keywords: HLS High Level Synthesis FPGA HDL Verilog VHDL EDA
Platform: UNKNOWN
